{"doc_id": "325ffda4-bb2a-4b4c-a3d5-3e24ecb04abb", "doc_name": "Model2", "doc_version": "0ee85558ba29d4ddb5f8214fa7a61c92", "format": "tf_js", "version": 27, "inputs": {"Image": {"dtype": "float32", "shape": [null, 224, 224, 3], "name": "Image:0"}}, "outputs": {"Confidences": {"dtype": "float32", "shape": [null, 3], "name": "325ffda4-bb2a-4b4c-a3d5-3e24ecb04abb.0d804e62-a48b-4b03-b99d-073cc5e155dc/dense_2/Softmax:0"}}, "tags": null, "classes": {"Label": ["Correct", "Covered", "Rotated"]}, "filename": "model.json", "export_model_version": 1}